ms_file_reader/__init__.py
ms_file_reader/common_ms.py
ms_file_reader/jcamp.py
ms_file_reader/massbank.py
ms_file_reader/msp.py
ms_file_reader-0.1.1.dist-info/licenses/LICENSE
ms_file_reader-0.1.1.dist-info/METADATA
ms_file_reader-0.1.1.dist-info/WHEEL
ms_file_reader-0.1.1.dist-info/top_level.txt
ms_file_reader-0.1.1.dist-info/RECORD
