Metadata-Version: 2.4
Name: ms_file_reader
Version: 0.1.1
Summary: Reads a few common file formats for processed mass spectra and generates consistent objects from them.
Author: Gregory Janesch
License-Expression: MIT
Project-URL: Homepage, https://github.com/gjanesch/ms-file-reader
Project-URL: Issues, https://github.com/gjanesch/ms-file-reader/issues
Keywords: mass spectrometry,jcamp,massbank,msp
Classifier: Operating System :: OS Independent
Classifier: Topic :: Scientific/Engineering :: Chemistry
Classifier: Topic :: Text Processing
Requires-Python: >=3.9
License-File: LICENSE
Requires-Dist: numpy
Dynamic: license-file
